rmk2/__init__.py
rmk2/api.py
rmk2/file.py
rmk2/hash.py
rmk2/config/__init__.py
rmk2/config/mapping.py
rmk2/data/__init__.py
rmk2/data/dictionary.py
rmk2/data/object.py
venv/bin/activate_this.py
venv/bin/rst2html.py
venv/bin/rst2html4.py
venv/bin/rst2html5.py
venv/bin/rst2latex.py
venv/bin/rst2man.py
venv/bin/rst2odt.py
venv/bin/rst2odt_prepstyles.py
venv/bin/rst2pseudoxml.py
venv/bin/rst2s5.py
venv/bin/rst2xetex.py
venv/bin/rst2xml.py
venv/bin/rstpep2html.py
rmk2_py-0.2.1.dist-info/LICENSE
rmk2_py-0.2.1.dist-info/METADATA
rmk2_py-0.2.1.dist-info/WHEEL
rmk2_py-0.2.1.dist-info/top_level.txt
rmk2_py-0.2.1.dist-info/RECORD
