Metadata-Version: 2.1
Name: rmk2-py
Version: 0.2.1
Summary: rmk2's Python Toolbox
Author-email: rmk2 <ryko@rmk2.org>
License: GPL-3.0-or-later
Project-URL: Repository, https://gitlab.com/rmk2/rmk2-py
Requires-Python: >=3.11
License-File: LICENSE
